main/__init__.py
main/new_sweep.py
main/pingsweep.py
main/ps.py
main/sweeper.py
pingsweeper-1.0.0.dist-info/METADATA
pingsweeper-1.0.0.dist-info/WHEEL
pingsweeper-1.0.0.dist-info/entry_points.txt
pingsweeper-1.0.0.dist-info/top_level.txt
pingsweeper-1.0.0.dist-info/RECORD
