Metadata-Version: 2.1
Name: pingsweeper
Version: 1.0.0
Summary: A tool for pinging subnets.
Home-page: https://github.com/jzmack/pingsweep
Author: Jacob Mackin
Author-email: mackinjz412@gmail.com
Classifier: Programming Language :: Python :: 3
Classifier: License :: OSI Approved :: MIT License
Classifier: Operating System :: OS Independent
Requires-Python: >3.7
